{
  "package-id": "hl7.fhir.uv.radiation-dose-summary",
  "title": "Radiation Dose Summary for Diagnostic Procedures on FHIR",
  "canonical": "http://hl7.org/fhir/uv/radiation-dose-summary",
  "introduction": "Radiation Dose Summary for Diagnostic Procedures on FHIR standardizes the sharing of minimal radiation information following a performed exam.",
  "category": "Diagnostics",
  "list": [
    {
      "version": "current",
      "desc": "Continuous Integration Build (latest in version control)",
      "path": "http://build.fhir.org/ig/HL7/fhir-radiation-dose-summary-ig",
      "fhirversion": "4.0.1",
      "status": "ci-build",
      "current": true
    },
    {
      "version": "0.1.0",
      "date": "2022-01-13",
      "desc": "January 2022 Ballot Reconciliation",
      "path": "http://hl7.org/fhir/uv/radiation-dose-summary/2022Jan",
      "sequence": "STU 1",
      "fhirversion": "4.0.1",
      "status": "ballot",
      "current": true
    }
  ]
}
